src/__init__.py
src/_default.py
src/_extended_model.py
src/_model.py
src/_utils.py
3DefficientNet-1.1.0.dist-info/METADATA
3DefficientNet-1.1.0.dist-info/WHEEL
3DefficientNet-1.1.0.dist-info/top_level.txt
3DefficientNet-1.1.0.dist-info/RECORD
